pipconf/__init__.py
pipconf/__main__.py
pipconf/cli.py
pipconf/configs.py
pipconf/consts.py
pipconf/templates/pip.conf
pipconf-2.0.1.dist-info/LICENSE
pipconf-2.0.1.dist-info/METADATA
pipconf-2.0.1.dist-info/WHEEL
pipconf-2.0.1.dist-info/entry_points.txt
pipconf-2.0.1.dist-info/RECORD
