Metadata-Version: 2.1
Name: pipconf
Version: 2.0.1
Summary: Python's PIP configuration manager
Home-page: https://github.com/jjpaulo2/pipconf
License: BSD-2-Clause
Keywords: configurations,configs,settings,pip,pip.conf
Author: João Paulo Carvalho
Author-email: jjpaulo2@protonmail.com
Requires-Python: >=3.9,<4.0
Classifier: Environment :: Console
Classifier: License :: OSI Approved :: BSD License
Classifier: Programming Language :: Python :: 3
Classifier: Programming Language :: Python :: 3.9
Classifier: Programming Language :: Python :: 3.10
Classifier: Programming Language :: Python :: 3.11
Classifier: Programming Language :: Python :: 3.12
Classifier: Topic :: Utilities
Classifier: Typing :: Typed
Requires-Dist: rich (>=13.7.1,<14.0.0)
Requires-Dist: typer (>=0.9.0,<0.10.0)
Project-URL: Bug Tracker, https://github.com/jjpaulo2/pipconf/issues
Project-URL: Documentation, https://jjpaulo2.github.io/pipconf/
Project-URL: Repository, https://github.com/jjpaulo2/pipconf
